devs_common/__init__.py
devs_common/config.py
devs_common/devs_config.py
devs_common/exceptions.py
devs_common/core/__init__.py
devs_common/core/container.py
devs_common/core/project.py
devs_common/core/workspace.py
devs_common/templates/Dockerfile
devs_common/templates/devcontainer.json
devs_common/templates/vscode-settings-reference.md
devs_common/templates/scripts/copy-ssh.sh
devs_common/templates/scripts/post-create-wrapper.sh
devs_common/templates/scripts/python-venv-integration.sh
devs_common/templates/scripts/screenshot-webapp.sh
devs_common/templates/scripts/setup-workspace.sh
devs_common/templates/scripts/webapp-screenshot.py
devs_common/templates/sudo-scripts/init-firewall.sh
devs_common/templates/sudo-scripts/setup-devs-env.sh
devs_common/templates/sudo-scripts/setup-vscode-cache.sh
devs_common/templates/sudo-scripts/start-services.sh
devs_common/utils/__init__.py
devs_common/utils/config_hash.py
devs_common/utils/console.py
devs_common/utils/devcontainer.py
devs_common/utils/devcontainer_template.py
devs_common/utils/docker_client.py
devs_common/utils/file_utils.py
devs_common/utils/git_utils.py
devs_common-1.2.1.dist-info/licenses/LICENSE
devs_common-1.2.1.dist-info/METADATA
devs_common-1.2.1.dist-info/WHEEL
devs_common-1.2.1.dist-info/top_level.txt
devs_common-1.2.1.dist-info/RECORD
